dynamic_world/__init__.py
dynamic_world/calculations.py
dynamic_world/configurations.py
dynamic_world/constants.py
dynamic_world/downloads.py
dynamic_world/errors.py
dynamic_world/utils.py
dynamic_world-0.3.5.dist-info/LICENSE
dynamic_world-0.3.5.dist-info/WHEEL
dynamic_world-0.3.5.dist-info/METADATA
dynamic_world-0.3.5.dist-info/RECORD
