Metadata-Version: 2.1
Name: dynamic-world
Version: 0.3.5
Summary: Land-use land-cover analysis using Dynamic World App from Earth Engine
Home-page: https://reforestum.com/
License: CC-BY-4.0
Author: Reforestum team
Author-email: info@reforestum.com
Requires-Python: >=3.9,<4.0
Classifier: License :: Other/Proprietary License
Classifier: Programming Language :: Python :: 3
Classifier: Programming Language :: Python :: 3.10
Classifier: Programming Language :: Python :: 3.9
Requires-Dist: PyYAML (>=6.0,<7.0)
Requires-Dist: earthengine-api (>=0.1.316,<0.2.0)
Requires-Dist: geedim (>=1.2.0,<2.0.0)
Requires-Dist: geemap (>=0.15.3,<0.16.0)
Requires-Dist: geojson (>=2.5.0,<3.0.0)
Requires-Dist: pydantic (>=1.9.1,<2.0.0)
Requires-Dist: typer (>=0.5.0,<0.6.0)
Project-URL: Repository, https://github.com/Reforestum/dynamic-world
